sham/__init__.py
sham_py-0.0.0.dist-info/WHEEL
sham_py-0.0.0.dist-info/METADATA
sham_py-0.0.0.dist-info/RECORD
